tqdm_rich/__init__.py
tqdm_rich/py.typed
tqdm_rich-0.1.1.dist-info/WHEEL
tqdm_rich-0.1.1.dist-info/METADATA
tqdm_rich-0.1.1.dist-info/RECORD
