Metadata-Version: 2.3
Name: tqdm-rich
Version: 0.1.1
Summary: A thread-safe tqdm-compatible progress bar library using Rich
Author: DawnMagnet
Author-email: DawnMagnet <axccjqh@qq.com>
License: MIT
Requires-Dist: rich>=10.0.0
Requires-Dist: pytest>=7.0.0 ; extra == 'dev'
Requires-Dist: pytest-cov>=4.0.0 ; extra == 'dev'
Requires-Dist: black>=23.0.0 ; extra == 'dev'
Requires-Dist: ruff>=0.1.0 ; extra == 'dev'
Requires-Dist: mypy>=1.0.0 ; extra == 'dev'
Requires-Python: >=3.8
Project-URL: Bug Tracker, https://github.com/DawnMagnet/tqdm-rich/issues
Project-URL: Documentation, https://github.com/DawnMagnet/tqdm-rich#readme
Project-URL: Homepage, https://github.com/DawnMagnet/tqdm-rich
Project-URL: Repository, https://github.com/DawnMagnet/tqdm-rich
Provides-Extra: dev
